[
    {
        "key": "datr",
        "value": "5CmTaHjuhcFybaHbDdwtZXH1",
        "domain": "facebook.com",
        "path": "/",
        "hostOnly": false,
        "creation": "2026-01-30T18:22:00.125Z",
        "lastAccessed": "2026-01-30T18:22:00.126Z"
    },
    {
        "key": "sb",
        "value": "5CmTaHcSkHEBkemzfsHgRszQ",
        "domain": "facebook.com",
        "path": "/",
        "hostOnly": false,
        "creation": "2026-01-30T18:22:00.126Z",
        "lastAccessed": "2026-01-30T18:22:00.126Z"
    },
    {
        "key": "ps_l",
        "value": "1",
        "domain": "facebook.com",
        "path": "/",
        "hostOnly": false,
        "creation": "2026-01-30T18:22:00.126Z",
        "lastAccessed": "2026-01-30T18:22:00.126Z"
    },
    {
        "key": "ps_n",
        "value": "1",
        "domain": "facebook.com",
        "path": "/",
        "hostOnly": false,
        "creation": "2026-01-30T18:22:00.126Z",
        "lastAccessed": "2026-01-30T18:22:00.126Z"
    },
    {
        "key": "pas",
        "value": "61576317202131%3AvdLlyAgn3h%2C61577970062022%3ASLwlLJq3hp%2C61579782003940%3Ahto28pyB0f%2C61580351432771%3A4MNI0msKA4%2C61580405860801%3Azfw7YdRb6v%2C61580538224148%3AIgr7D8uVs5%2C61580225713158%3ApwzY8qKPH1",
        "domain": "facebook.com",
        "path": "/",
        "hostOnly": false,
        "creation": "2026-01-30T18:22:00.126Z",
        "lastAccessed": "2026-01-30T18:22:00.126Z"
    },
    {
        "key": "oo",
        "value": "v1",
        "domain": "facebook.com",
        "path": "/",
        "hostOnly": false,
        "creation": "2026-01-30T18:22:00.126Z",
        "lastAccessed": "2026-01-30T18:22:00.126Z"
    },
    {
        "key": "dpr",
        "value": "1.75",
        "domain": "facebook.com",
        "path": "/",
        "hostOnly": false,
        "creation": "2026-01-30T18:22:00.126Z",
        "lastAccessed": "2026-01-30T18:22:00.126Z"
    },
    {
        "key": "locale",
        "value": "en_US",
        "domain": "facebook.com",
        "path": "/",
        "hostOnly": false,
        "creation": "2026-01-30T18:22:00.126Z",
        "lastAccessed": "2026-01-30T18:22:00.126Z"
    },
    {
        "key": "c_user",
        "value": "61587180571314",
        "domain": "facebook.com",
        "path": "/",
        "hostOnly": false,
        "creation": "2026-01-30T18:22:00.126Z",
        "lastAccessed": "2026-01-30T18:22:00.126Z"
    },
    {
        "key": "fr",
        "value": "14xI1ocby192DMERy.AWcw6OBh98dL1hygYOVpsNj0I89ks1lHUO5V-3GYxOWj8cJSO8o.BpfPaJ..AAA.0.0.BpfPaJ.AWfiZ11I0qy4Ei4Y-ViNGJ1pzW0",
        "domain": "facebook.com",
        "path": "/",
        "hostOnly": false,
        "creation": "2026-01-30T18:22:00.126Z",
        "lastAccessed": "2026-01-30T18:22:00.126Z"
    },
    {
        "key": "xs",
        "value": "50%3ANrV4-JfVuKBhTA%3A2%3A1769797247%3A-1%3A-1%3A%3AAcxW6QVgA8Y--lLpblOQPdAiWxbaa4K1FAzBlb5Vow",
        "domain": "facebook.com",
        "path": "/",
        "hostOnly": false,
        "creation": "2026-01-30T18:22:00.126Z",
        "lastAccessed": "2026-01-30T18:22:00.126Z"
    },
    {
        "key": "presence",
        "value": "C%7B%22lm3%22%3A%22g.1189442276421716%22%2C%22t3%22%3A%5B%7B%22o%22%3A0%2C%22i%22%3A%22sc.25071175775890293%22%7D%2C%7B%22o%22%3A0%2C%22i%22%3A%22g.1461199735613151%22%7D%5D%2C%22utc3%22%3A1769797278101%2C%22v%22%3A1%7D",
        "domain": "facebook.com",
        "path": "/",
        "hostOnly": false,
        "creation": "2026-01-30T18:22:00.126Z",
        "lastAccessed": "2026-01-30T18:22:00.126Z"
    },
    {
        "key": "wd",
        "value": "980x1711",
        "domain": "facebook.com",
        "path": "/",
        "hostOnly": false,
        "creation": "2026-01-30T18:22:00.126Z",
        "lastAccessed": "2026-01-30T18:22:00.126Z"
    }
]
