[
    {
        "key": "dbln",
        "value": "%7B%2261580169657191%22%3A%224JGpsQHL%22%7D",
        "domain": "facebook.com",
        "path": "/login/device-based/",
        "hostOnly": false,
        "creation": "2026-02-05T21:16:52.888Z",
        "lastAccessed": "2026-02-05T21:16:52.888Z"
    },
    {
        "key": "sb",
        "value": "DyU0aUXPZdhDiTz6QFsO3pVp",
        "domain": "facebook.com",
        "path": "/",
        "hostOnly": false,
        "creation": "2026-02-05T21:16:52.888Z",
        "lastAccessed": "2026-02-05T21:16:52.888Z"
    },
    {
        "key": "ps_l",
        "value": "1",
        "domain": "facebook.com",
        "path": "/",
        "hostOnly": false,
        "creation": "2026-02-05T21:16:52.888Z",
        "lastAccessed": "2026-02-05T21:16:52.888Z"
    },
    {
        "key": "ps_n",
        "value": "1",
        "domain": "facebook.com",
        "path": "/",
        "hostOnly": false,
        "creation": "2026-02-05T21:16:52.888Z",
        "lastAccessed": "2026-02-05T21:16:52.888Z"
    },
    {
        "key": "locale",
        "value": "en_US",
        "domain": "facebook.com",
        "path": "/",
        "hostOnly": false,
        "creation": "2026-02-05T21:16:52.888Z",
        "lastAccessed": "2026-02-05T21:16:52.888Z"
    },
    {
        "key": "datr",
        "value": "9xh-acoasyQOVfc3yrcCTYHm",
        "domain": "facebook.com",
        "path": "/",
        "hostOnly": false,
        "creation": "2026-02-05T21:16:52.888Z",
        "lastAccessed": "2026-02-05T21:16:52.888Z"
    },
    {
        "key": "dpr",
        "value": "1.9240320920944214",
        "domain": "facebook.com",
        "path": "/",
        "hostOnly": false,
        "creation": "2026-02-05T21:16:52.888Z",
        "lastAccessed": "2026-02-05T21:16:52.888Z"
    },
    {
        "key": "wd",
        "value": "892x1660",
        "domain": "facebook.com",
        "path": "/",
        "hostOnly": false,
        "creation": "2026-02-05T21:16:52.888Z",
        "lastAccessed": "2026-02-05T21:16:52.888Z"
    },
    {
        "key": "c_user",
        "value": "61584864003939",
        "domain": "facebook.com",
        "path": "/",
        "hostOnly": false,
        "creation": "2026-02-05T21:16:52.888Z",
        "lastAccessed": "2026-02-05T21:16:52.888Z"
    },
    {
        "key": "xs",
        "value": "20%3APbcD6rBG7mLVhg%3A2%3A1770326143%3A-1%3A-1%3A%3AAczkRTN_7gT-LOipIu2VcODl5ZC08Rz1849JGOTVyw",
        "domain": "facebook.com",
        "path": "/",
        "hostOnly": false,
        "creation": "2026-02-05T21:16:52.888Z",
        "lastAccessed": "2026-02-05T21:16:52.888Z"
    },
    {
        "key": "fr",
        "value": "1yHWStWR4VsnLOVQ3.AWeSNKhRKZMhWJnhUb0dV8zdFFVyRtzgnUUuAmykhvHx_ZTmbj0.BphQiE..AAA.0.0.BphQiI.AWdwihKJZtDQj2OS4l0Li09QsKw",
        "domain": "facebook.com",
        "path": "/",
        "hostOnly": false,
        "creation": "2026-02-05T21:16:52.888Z",
        "lastAccessed": "2026-02-05T21:16:52.888Z"
    },
    {
        "key": "presence",
        "value": "C%7B%22t3%22%3A%5B%5D%2C%22utc3%22%3A1770326162150%2C%22v%22%3A1%7D",
        "domain": "facebook.com",
        "path": "/",
        "hostOnly": false,
        "creation": "2026-02-05T21:16:52.888Z",
        "lastAccessed": "2026-02-05T21:16:52.888Z"
    }
]
